cage.py
PYCage-0.2.0.dist-info/DESCRIPTION.rst
PYCage-0.2.0.dist-info/METADATA
PYCage-0.2.0.dist-info/RECORD
PYCage-0.2.0.dist-info/WHEEL
PYCage-0.2.0.dist-info/entry_points.txt
PYCage-0.2.0.dist-info/metadata.json
PYCage-0.2.0.dist-info/top_level.txt
cage/__init__.py
cage/container/__init__.py
cage/container/handler.py
cage/env/EnvHandler.py
cage/env/__init__.py
cage/env/env_handler.py
cage/env/scripts/activate.sh
cage/env/scripts/pip.sh
cage/env/scripts/python.sh
cage/tests/__init__.py
cage/tests/test_container_handler.py
cage/tests/test_app/__init__.py
cage/tests/test_app/main.py
