Metadata-Version: 2.0
Name: PYCage
Version: 0.2.0
Summary: Develop and run your Python applications in clean Docker environments
Home-page: https://github.com/macostea/cage
Author: Mihai Costea
Author-email: mihai.andrei.costea@icloud.com
License: MIT
Keywords: setuptools deployment installation distutils docker
Platform: UNKNOWN
Classifier: Development Status :: 3 - Alpha
Classifier: Intended Audience :: Developers
Classifier: Topic :: Software Development :: Libraries
Classifier: License :: OSI Approved :: MIT License
Classifier: Programming Language :: Python :: 3.5
Requires-Dist: docker-py
